{"data":{"heads":[{"caption":"商品编码","field":"number"},{"caption":"商品名称","field":"name"},{"caption":"辅助属性","field":"skuName"},{"caption":"品牌","field":"brandName"},{"caption":"类别","field":"categoryName"},{"caption":"规格型号","field":"productModel"}],"rows":[{"auxpropid":0,"auxpropname":"","barcode":"","brandName":"","categoryName":"小百货","isSerNum":0,"itemid":10943919893,"memberprice":9,"name":"芙蓉王","number":"0005","prices":[{"id":10910394973,"inventoryId":10943919893,"purPrice":0,"retailPrice":120,"salePrice":216,"salePrice1":108,"salePrice2":88,"salePrice3":0,"unitId":10921949113,"unitTypeId":10921949102},{"id":10911099450,"inventoryId":10943919893,"purPrice":0,"retailPrice":10,"salePrice":18,"salePrice1":9,"salePrice2":88,"salePrice3":70,"unitId":10921949109,"unitTypeId":10921949102}],"productModel":"","qty":4487,"reatailprice":18,"skuName":"","skuNumber":"0005","skuid":0,"skus":[],"unitTypeId":10921949102,"unitTypeName":"香烟","unitid":10921949109,"unitname":"包"},{"auxpropid":0,"auxpropname":"","barcode":"","brandName":"","categoryName":"小百货","isSerNum":1,"itemid":109105939661,"memberprice":16,"name":"系列号商品","number":"0006","prices":[{"id":10910394960,"inventoryId":109105939661,"purPrice":0,"retailPrice":18,"salePrice":20,"salePrice1":16,"salePrice2":0,"salePrice3":0,"unitId":109105939646,"unitTypeId":109105939638},{"id":10910394963,"inventoryId":109105939661,"purPrice":0,"retailPrice":180,"salePrice":200,"salePrice1":0,"salePrice2":0,"salePrice3":0,"unitId":109105939650,"unitTypeId":109105939638}],"productModel":"","qty":32,"reatailprice":20,"skuName":"","skuNumber":"0006","skuid":0,"skus":[],"unitTypeId":109105939638,"unitTypeName":"计量","unitid":109105939646,"unitname":"包"},{"auxpropid":0,"auxpropname":"","barcode":"","brandName":"","categoryName":"小百货","isSerNum":1,"itemid":10912899325,"memberprice":0,"name":"小米手机6","number":"0007","productModel":"","qty":17,"reatailprice":1999,"skuName":"","skuNumber":"0007","skuid":0,"skus":[],"unitTypeId":109105939638,"unitTypeName":"计量","unitid":109105939642,"unitname":"个"},{"auxpropid":10921949191,"auxpropname":"红色/L","barcode":"","brandName":"","categoryName":"小百货","isSerNum":1,"itemid":10912899350,"memberprice":8,"name":"系列号xxx","number":"0008","productModel":"","qty":3,"reatailprice":15,"skuName":"红色/L","skuNumber":"0008_1","skuid":10921949191,"skus":[{"barcode":"","invId":10912899350,"memberprice":8,"number":"0008_1","retailPrice":15,"salePrice":15,"skuAssistId":"10921949135,10921949126","skuName":"红色/L","skuid":10921949191},{"barcode":"","invId":10912899350,"memberprice":0,"number":"0008_2","retailPrice":15,"salePrice":15,"skuAssistId":"10921949135,10921949128","skuName":"红色/M","skuid":10921949192},{"barcode":"","invId":10912899350,"memberprice":0,"number":"0008_3","retailPrice":15,"salePrice":15,"skuAssistId":"10921949137,10921949126","skuName":"蓝色/L","skuid":10921949193},{"barcode":"","invId":10912899350,"memberprice":0,"number":"0008_4","retailPrice":15,"salePrice":15,"skuAssistId":"10921949137,10921949128","skuName":"蓝色/M","skuid":10921949194}],"unitTypeId":10921949105,"unitTypeName":"服装","unitid":10921949118,"unitname":"件"},{"auxpropid":10921949192,"auxpropname":"红色/M","barcode":"","brandName":"","categoryName":"小百货","isSerNum":1,"itemid":10912899350,"memberprice":0,"name":"系列号xxx","number":"0008","productModel":"","qty":11,"reatailprice":15,"skuName":"红色/M","skuNumber":"0008_2","skuid":10921949192,"skus":[{"barcode":"","invId":10912899350,"memberprice":8,"number":"0008_1","retailPrice":15,"salePrice":15,"skuAssistId":"10921949135,10921949126","skuName":"红色/L","skuid":10921949191},{"barcode":"","invId":10912899350,"memberprice":0,"number":"0008_2","retailPrice":15,"salePrice":15,"skuAssistId":"10921949135,10921949128","skuName":"红色/M","skuid":10921949192},{"barcode":"","invId":10912899350,"memberprice":0,"number":"0008_3","retailPrice":15,"salePrice":15,"skuAssistId":"10921949137,10921949126","skuName":"蓝色/L","skuid":10921949193},{"barcode":"","invId":10912899350,"memberprice":0,"number":"0008_4","retailPrice":15,"salePrice":15,"skuAssistId":"10921949137,10921949128","skuName":"蓝色/M","skuid":10921949194}],"unitTypeId":10921949105,"unitTypeName":"服装","unitid":10921949118,"unitname":"件"},{"auxpropid":10921949193,"auxpropname":"蓝色/L","barcode":"","brandName":"","categoryName":"小百货","isSerNum":1,"itemid":10912899350,"memberprice":0,"name":"系列号xxx","number":"0008","productModel":"","qty":15,"reatailprice":15,"skuName":"蓝色/L","skuNumber":"0008_3","skuid":10921949193,"skus":[{"barcode":"","invId":10912899350,"memberprice":8,"number":"0008_1","retailPrice":15,"salePrice":15,"skuAssistId":"10921949135,10921949126","skuName":"红色/L","skuid":10921949191},{"barcode":"","invId":10912899350,"memberprice":0,"number":"0008_2","retailPrice":15,"salePrice":15,"skuAssistId":"10921949135,10921949128","skuName":"红色/M","skuid":10921949192},{"barcode":"","invId":10912899350,"memberprice":0,"number":"0008_3","retailPrice":15,"salePrice":15,"skuAssistId":"10921949137,10921949126","skuName":"蓝色/L","skuid":10921949193},{"barcode":"","invId":10912899350,"memberprice":0,"number":"0008_4","retailPrice":15,"salePrice":15,"skuAssistId":"10921949137,10921949128","skuName":"蓝色/M","skuid":10921949194}],"unitTypeId":10921949105,"unitTypeName":"服装","unitid":10921949118,"unitname":"件"},{"auxpropid":10921949194,"auxpropname":"蓝色/M","barcode":"","brandName":"","categoryName":"小百货","isSerNum":1,"itemid":10912899350,"memberprice":0,"name":"系列号xxx","number":"0008","productModel":"","qty":8,"reatailprice":15,"skuName":"蓝色/M","skuNumber":"0008_4","skuid":10921949194,"skus":[{"barcode":"","invId":10912899350,"memberprice":8,"number":"0008_1","retailPrice":15,"salePrice":15,"skuAssistId":"10921949135,10921949126","skuName":"红色/L","skuid":10921949191},{"barcode":"","invId":10912899350,"memberprice":0,"number":"0008_2","retailPrice":15,"salePrice":15,"skuAssistId":"10921949135,10921949128","skuName":"红色/M","skuid":10921949192},{"barcode":"","invId":10912899350,"memberprice":0,"number":"0008_3","retailPrice":15,"salePrice":15,"skuAssistId":"10921949137,10921949126","skuName":"蓝色/L","skuid":10921949193},{"barcode":"","invId":10912899350,"memberprice":0,"number":"0008_4","retailPrice":15,"salePrice":15,"skuAssistId":"10921949137,10921949128","skuName":"蓝色/M","skuid":10921949194}],"unitTypeId":10921949105,"unitTypeName":"服装","unitid":10921949118,"unitname":"件"},{"auxpropid":0,"auxpropname":"","barcode":"111122322","brandName":"","categoryName":"小百货","isSerNum":0,"itemid":10921949164,"memberprice":0,"name":"大中华香烟","number":"001","prices":[{"id":1091109970,"inventoryId":10921949164,"purPrice":0,"retailPrice":0,"salePrice":0,"salePrice1":0,"salePrice2":0,"salePrice3":0,"unitId":10921949113,"unitTypeId":10921949102},{"id":10921949168,"inventoryId":10921949164,"purPrice":0,"retailPrice":10,"salePrice":20,"salePrice1":0,"salePrice2":0,"salePrice3":0,"unitId":10921949109,"unitTypeId":10921949102}],"productModel":"规格型号","qty":4704,"reatailprice":20,"skuName":"","skuNumber":"001","skuid":0,"skus":[],"unitTypeId":10921949102,"unitTypeName":"香烟","unitid":10921949109,"unitname":"包"},{"auxpropid":10921949191,"auxpropname":"红色/L","barcode":"00102001","brandName":"","categoryName":"服装","isSerNum":0,"itemid":1091849922,"memberprice":0,"name":"测试单位","number":"00102","prices":[{"id":10918499124,"inventoryId":1091849922,"purPrice":0,"retailPrice":0,"salePrice":0,"salePrice1":0,"salePrice2":0,"salePrice3":0,"unitId":109105939642,"unitTypeId":109105939638},{"id":10918499128,"inventoryId":1091849922,"purPrice":0,"retailPrice":0,"salePrice":0,"salePrice1":0,"salePrice2":0,"salePrice3":0,"unitId":109105939646,"unitTypeId":109105939638}],"productModel":"","qty":0,"reatailprice":0,"skuName":"红色/L","skuNumber":"00102_1","skuid":10921949191,"skus":[{"barcode":"00102001","invId":1091849922,"memberprice":0,"number":"00102_1","retailPrice":0,"salePrice":0,"skuAssistId":"10921949135,10921949126","skuName":"红色/L","skuid":10921949191},{"barcode":"","invId":1091849922,"memberprice":0,"number":"00102_3","retailPrice":0,"salePrice":0,"skuAssistId":"10921949135,10921949128","skuName":"红色/M","skuid":10921949192},{"barcode":"","invId":1091849922,"memberprice":0,"number":"00102_4","retailPrice":0,"salePrice":0,"skuAssistId":"10921949137,10921949126","skuName":"蓝色/L","skuid":10921949193},{"barcode":"","invId":1091849922,"memberprice":0,"number":"00102_5","retailPrice":0,"salePrice":0,"skuAssistId":"10921949137,10921949128","skuName":"蓝色/M","skuid":10921949194}],"unitTypeId":109105939638,"unitTypeName":"计量","unitid":109105939642,"unitname":"个"},{"auxpropid":10921949192,"auxpropname":"红色/M","barcode":"","brandName":"","categoryName":"服装","isSerNum":0,"itemid":1091849922,"memberprice":0,"name":"测试单位","number":"00102","prices":[{"id":10918499124,"inventoryId":1091849922,"purPrice":0,"retailPrice":0,"salePrice":0,"salePrice1":0,"salePrice2":0,"salePrice3":0,"unitId":109105939642,"unitTypeId":109105939638},{"id":10918499128,"inventoryId":1091849922,"purPrice":0,"retailPrice":0,"salePrice":0,"salePrice1":0,"salePrice2":0,"salePrice3":0,"unitId":109105939646,"unitTypeId":109105939638}],"productModel":"","qty":0,"reatailprice":0,"skuName":"红色/M","skuNumber":"00102_3","skuid":10921949192,"skus":[{"barcode":"00102001","invId":1091849922,"memberprice":0,"number":"00102_1","retailPrice":0,"salePrice":0,"skuAssistId":"10921949135,10921949126","skuName":"红色/L","skuid":10921949191},{"barcode":"","invId":1091849922,"memberprice":0,"number":"00102_3","retailPrice":0,"salePrice":0,"skuAssistId":"10921949135,10921949128","skuName":"红色/M","skuid":10921949192},{"barcode":"","invId":1091849922,"memberprice":0,"number":"00102_4","retailPrice":0,"salePrice":0,"skuAssistId":"10921949137,10921949126","skuName":"蓝色/L","skuid":10921949193},{"barcode":"","invId":1091849922,"memberprice":0,"number":"00102_5","retailPrice":0,"salePrice":0,"skuAssistId":"10921949137,10921949128","skuName":"蓝色/M","skuid":10921949194}],"unitTypeId":109105939638,"unitTypeName":"计量","unitid":109105939642,"unitname":"个"},{"auxpropid":10921949193,"auxpropname":"蓝色/L","barcode":"","brandName":"","categoryName":"服装","isSerNum":0,"itemid":1091849922,"memberprice":0,"name":"测试单位","number":"00102","prices":[{"id":10918499124,"inventoryId":1091849922,"purPrice":0,"retailPrice":0,"salePrice":0,"salePrice1":0,"salePrice2":0,"salePrice3":0,"unitId":109105939642,"unitTypeId":109105939638},{"id":10918499128,"inventoryId":1091849922,"purPrice":0,"retailPrice":0,"salePrice":0,"salePrice1":0,"salePrice2":0,"salePrice3":0,"unitId":109105939646,"unitTypeId":109105939638}],"productModel":"","qty":0,"reatailprice":0,"skuName":"蓝色/L","skuNumber":"00102_4","skuid":10921949193,"skus":[{"barcode":"00102001","invId":1091849922,"memberprice":0,"number":"00102_1","retailPrice":0,"salePrice":0,"skuAssistId":"10921949135,10921949126","skuName":"红色/L","skuid":10921949191},{"barcode":"","invId":1091849922,"memberprice":0,"number":"00102_3","retailPrice":0,"salePrice":0,"skuAssistId":"10921949135,10921949128","skuName":"红色/M","skuid":10921949192},{"barcode":"","invId":1091849922,"memberprice":0,"number":"00102_4","retailPrice":0,"salePrice":0,"skuAssistId":"10921949137,10921949126","skuName":"蓝色/L","skuid":10921949193},{"barcode":"","invId":1091849922,"memberprice":0,"number":"00102_5","retailPrice":0,"salePrice":0,"skuAssistId":"10921949137,10921949128","skuName":"蓝色/M","skuid":10921949194}],"unitTypeId":109105939638,"unitTypeName":"计量","unitid":109105939642,"unitname":"个"},{"auxpropid":10921949194,"auxpropname":"蓝色/M","barcode":"","brandName":"","categoryName":"服装","isSerNum":0,"itemid":1091849922,"memberprice":0,"name":"测试单位","number":"00102","prices":[{"id":10918499124,"inventoryId":1091849922,"purPrice":0,"retailPrice":0,"salePrice":0,"salePrice1":0,"salePrice2":0,"salePrice3":0,"unitId":109105939642,"unitTypeId":109105939638},{"id":10918499128,"inventoryId":1091849922,"purPrice":0,"retailPrice":0,"salePrice":0,"salePrice1":0,"salePrice2":0,"salePrice3":0,"unitId":109105939646,"unitTypeId":109105939638}],"productModel":"","qty":0,"reatailprice":0,"skuName":"蓝色/M","skuNumber":"00102_5","skuid":10921949194,"skus":[{"barcode":"00102001","invId":1091849922,"memberprice":0,"number":"00102_1","retailPrice":0,"salePrice":0,"skuAssistId":"10921949135,10921949126","skuName":"红色/L","skuid":10921949191},{"barcode":"","invId":1091849922,"memberprice":0,"number":"00102_3","retailPrice":0,"salePrice":0,"skuAssistId":"10921949135,10921949128","skuName":"红色/M","skuid":10921949192},{"barcode":"","invId":1091849922,"memberprice":0,"number":"00102_4","retailPrice":0,"salePrice":0,"skuAssistId":"10921949137,10921949126","skuName":"蓝色/L","skuid":10921949193},{"barcode":"","invId":1091849922,"memberprice":0,"number":"00102_5","retailPrice":0,"salePrice":0,"skuAssistId":"10921949137,10921949128","skuName":"蓝色/M","skuid":10921949194}],"unitTypeId":109105939638,"unitTypeName":"计量","unitid":109105939642,"unitname":"个"},{"auxpropid":10921949192,"auxpropname":"红色/M","barcode":"1111","brandName":"","categoryName":"服装","isSerNum":0,"itemid":10918499210,"memberprice":0,"name":"测试","number":"00103","productModel":"","qty":0,"reatailprice":0,"skuName":"红色/M","skuNumber":"00103_1","skuid":10921949192,"skus":[{"barcode":"1111","invId":10918499210,"memberprice":0,"number":"00103_1","retailPrice":0,"salePrice":0,"skuAssistId":"10921949135,10921949128","skuName":"红色/M","skuid":10921949192},{"barcode":"22222","invId":10918499210,"memberprice":0,"number":"00103_2","retailPrice":0,"salePrice":0,"skuAssistId":"10921949135,10921949130","skuName":"红色/S","skuid":109118939140}],"unitTypeId":109105939638,"unitTypeName":"计量","unitid":109105939642,"unitname":"个"},{"auxpropid":109118939140,"auxpropname":"红色/S","barcode":"22222","brandName":"","categoryName":"服装","isSerNum":0,"itemid":10918499210,"memberprice":0,"name":"测试","number":"00103","productModel":"","qty":0,"reatailprice":0,"skuName":"红色/S","skuNumber":"00103_2","skuid":109118939140,"skus":[{"barcode":"1111","invId":10918499210,"memberprice":0,"number":"00103_1","retailPrice":0,"salePrice":0,"skuAssistId":"10921949135,10921949128","skuName":"红色/M","skuid":10921949192},{"barcode":"22222","invId":10918499210,"memberprice":0,"number":"00103_2","retailPrice":0,"salePrice":0,"skuAssistId":"10921949135,10921949130","skuName":"红色/S","skuid":109118939140}],"unitTypeId":109105939638,"unitTypeName":"计量","unitid":109105939642,"unitname":"个"},{"auxpropid":0,"auxpropname":"","barcode":"pcsp0018","brandName":"","categoryName":"数码3C","isSerNum":0,"itemid":109103949305,"memberprice":9.8,"name":"批次商品","number":"0018","prices":[{"id":109103949328,"inventoryId":109103949305,"purPrice":0,"retailPrice":9.5,"salePrice":9.9,"salePrice1":9.8,"salePrice2":0,"salePrice3":0,"unitId":109105939642,"unitTypeId":109105939638},{"id":109103949329,"inventoryId":109103949305,"purPrice":0,"retailPrice":59,"salePrice":59,"salePrice1":58,"salePrice2":0,"salePrice3":0,"unitId":109105939646,"unitTypeId":109105939638}],"productModel":"","qty":13152,"reatailprice":9.9,"skuName":"","skuNumber":"0018","skuid":0,"skus":[],"unitTypeId":109105939638,"unitTypeName":"计量","unitid":109105939642,"unitname":"个"},{"auxpropid":10937913915,"auxpropname":"红色","barcode":"","brandName":"","categoryName":"小百货","isSerNum":0,"itemid":10937913917,"memberprice":0,"name":"批次0019","number":"0019","productModel":"","qty":20,"reatailprice":0,"skuName":"红色","skuNumber":"0019_1","skuid":10937913915,"skus":[{"barcode":"","invId":10937913917,"memberprice":0,"number":"0019_1","retailPrice":0,"salePrice":0,"skuAssistId":"10921949135","skuName":"红色","skuid":10937913915},{"barcode":"","invId":10937913917,"memberprice":0,"number":"0019_2","retailPrice":0,"salePrice":0,"skuAssistId":"10921949137","skuName":"蓝色","skuid":10937913916}],"unitTypeId":109105939638,"unitTypeName":"计量","unitid":109105939646,"unitname":"包"},{"auxpropid":10937913916,"auxpropname":"蓝色","barcode":"","brandName":"","categoryName":"小百货","isSerNum":0,"itemid":10937913917,"memberprice":0,"name":"批次0019","number":"0019","productModel":"","qty":0,"reatailprice":0,"skuName":"蓝色","skuNumber":"0019_2","skuid":10937913916,"skus":[{"barcode":"","invId":10937913917,"memberprice":0,"number":"0019_1","retailPrice":0,"salePrice":0,"skuAssistId":"10921949135","skuName":"红色","skuid":10937913915},{"barcode":"","invId":10937913917,"memberprice":0,"number":"0019_2","retailPrice":0,"salePrice":0,"skuAssistId":"10921949137","skuName":"蓝色","skuid":10937913916}],"unitTypeId":109105939638,"unitTypeName":"计量","unitid":109105939646,"unitname":"包"},{"auxpropid":0,"auxpropname":"","barcode":"","brandName":"","categoryName":"小百货","isSerNum":0,"itemid":10912899227,"memberprice":0,"name":"小李飞刀","number":"002","prices":[{"id":10912899239,"inventoryId":10912899227,"purPrice":0,"retailPrice":180,"salePrice":200,"salePrice1":0,"salePrice2":0,"salePrice3":0,"unitId":10912899215,"unitTypeId":10912899211},{"id":10912899301,"inventoryId":10912899227,"purPrice":0,"retailPrice":0,"salePrice":0,"salePrice1":0,"salePrice2":0,"salePrice3":0,"unitId":10912899219,"unitTypeId":10912899211}],"productModel":"","qty":0,"reatailprice":200,"skuName":"","skuNumber":"002","skuid":0,"skus":[],"unitTypeId":10912899211,"unitTypeName":"刀","unitid":10912899215,"unitname":"把"},{"auxpropid":10937913915,"auxpropname":"红色","barcode":"","brandName":"","categoryName":"小百货","isSerNum":0,"itemid":10937913941,"memberprice":0,"name":"保质期0020","number":"0020","productModel":"","qty":10,"reatailprice":0,"skuName":"红色","skuNumber":"0020_1","skuid":10937913915,"skus":[{"barcode":"","invId":10937913941,"memberprice":0,"number":"0020_1","retailPrice":0,"salePrice":0,"skuAssistId":"10921949135","skuName":"红色","skuid":10937913915},{"barcode":"","invId":10937913941,"memberprice":0,"number":"0020_2","retailPrice":20,"salePrice":20,"skuAssistId":"10921949137","skuName":"蓝色","skuid":10937913916}],"unitTypeId":10921949102,"unitTypeName":"香烟","unitid":10921949109,"unitname":"包"},{"auxpropid":10937913916,"auxpropname":"蓝色","barcode":"","brandName":"","categoryName":"小百货","isSerNum":0,"itemid":10937913941,"memberprice":0,"name":"保质期0020","number":"0020","productModel":"","qty":21,"reatailprice":20,"skuName":"蓝色","skuNumber":"0020_2","skuid":10937913916,"skus":[{"barcode":"","invId":10937913941,"memberprice":0,"number":"0020_1","retailPrice":0,"salePrice":0,"skuAssistId":"10921949135","skuName":"红色","skuid":10937913915},{"barcode":"","invId":10937913941,"memberprice":0,"number":"0020_2","retailPrice":20,"salePrice":20,"skuAssistId":"10921949137","skuName":"蓝色","skuid":10937913916}],"unitTypeId":10921949102,"unitTypeName":"香烟","unitid":10921949109,"unitname":"包"},{"auxpropid":0,"auxpropname":"","barcode":"","brandName":"","categoryName":"生鲜","isSerNum":0,"itemid":10937913982,"memberprice":0,"name":"猪肉0021","number":"0021","productModel":"","qty":199.99,"reatailprice":0,"skuName":"","skuNumber":"0021","skuid":0,"skus":[],"unitTypeId":10937913966,"unitTypeName":"生鲜","unitid":10937913970,"unitname":"斤"},{"auxpropid":1091189391150,"auxpropname":"白色/XL","barcode":"","brandName":"","categoryName":"服装","isSerNum":0,"itemid":10921949195,"memberprice":0,"name":"耐克运动衣","number":"003","productModel":"规格型号哈哈","qty":0,"reatailprice":200,"skuName":"白色/XL","skuNumber":"003_5","skuid":1091189391150,"skus":[{"barcode":"","invId":10921949195,"memberprice":0,"number":"003_5","retailPrice":200,"salePrice":200,"skuAssistId":"1091189391144,1091189391136","skuName":"白色/XL","skuid":1091189391150},{"barcode":"","invId":10921949195,"memberprice":0,"number":"003_6","retailPrice":200,"salePrice":200,"skuAssistId":"1091189391144,1091189391138","skuName":"白色/XXL","skuid":1091189391151},{"barcode":"003001","invId":10921949195,"memberprice":0,"number":"003_1","retailPrice":200,"salePrice":200,"skuAssistId":"10921949135,10921949126","skuName":"红色/L","skuid":10921949191},{"barcode":"003002","invId":10921949195,"memberprice":0,"number":"003_2","retailPrice":195,"salePrice":195,"skuAssistId":"10921949135,10921949128","skuName":"红色/M","skuid":10921949192},{"barcode":"003003","invId":10921949195,"memberprice":0,"number":"003_3","retailPrice":200,"salePrice":200,"skuAssistId":"10921949137,10921949126","skuName":"蓝色/L","skuid":10921949193},{"barcode":"","invId":10921949195,"memberprice":0,"number":"003_4","retailPrice":200,"salePrice":200,"skuAssistId":"10921949137,10921949128","skuName":"蓝色/M","skuid":10921949194}],"unitTypeId":10921949105,"unitTypeName":"服装","unitid":10921949118,"unitname":"件"},{"auxpropid":1091189391151,"auxpropname":"白色/XXL","barcode":"","brandName":"","categoryName":"服装","isSerNum":0,"itemid":10921949195,"memberprice":0,"name":"耐克运动衣","number":"003","productModel":"规格型号哈哈","qty":0,"reatailprice":200,"skuName":"白色/XXL","skuNumber":"003_6","skuid":1091189391151,"skus":[{"barcode":"","invId":10921949195,"memberprice":0,"number":"003_5","retailPrice":200,"salePrice":200,"skuAssistId":"1091189391144,1091189391136","skuName":"白色/XL","skuid":1091189391150},{"barcode":"","invId":10921949195,"memberprice":0,"number":"003_6","retailPrice":200,"salePrice":200,"skuAssistId":"1091189391144,1091189391138","skuName":"白色/XXL","skuid":1091189391151},{"barcode":"003001","invId":10921949195,"memberprice":0,"number":"003_1","retailPrice":200,"salePrice":200,"skuAssistId":"10921949135,10921949126","skuName":"红色/L","skuid":10921949191},{"barcode":"003002","invId":10921949195,"memberprice":0,"number":"003_2","retailPrice":195,"salePrice":195,"skuAssistId":"10921949135,10921949128","skuName":"红色/M","skuid":10921949192},{"barcode":"003003","invId":10921949195,"memberprice":0,"number":"003_3","retailPrice":200,"salePrice":200,"skuAssistId":"10921949137,10921949126","skuName":"蓝色/L","skuid":10921949193},{"barcode":"","invId":10921949195,"memberprice":0,"number":"003_4","retailPrice":200,"salePrice":200,"skuAssistId":"10921949137,10921949128","skuName":"蓝色/M","skuid":10921949194}],"unitTypeId":10921949105,"unitTypeName":"服装","unitid":10921949118,"unitname":"件"},{"auxpropid":10921949191,"auxpropname":"红色/L","barcode":"003001","brandName":"","categoryName":"服装","isSerNum":0,"itemid":10921949195,"memberprice":0,"name":"耐克运动衣","number":"003","productModel":"规格型号哈哈","qty":4969,"reatailprice":200,"skuName":"红色/L","skuNumber":"003_1","skuid":10921949191,"skus":[{"barcode":"","invId":10921949195,"memberprice":0,"number":"003_5","retailPrice":200,"salePrice":200,"skuAssistId":"1091189391144,1091189391136","skuName":"白色/XL","skuid":1091189391150},{"barcode":"","invId":10921949195,"memberprice":0,"number":"003_6","retailPrice":200,"salePrice":200,"skuAssistId":"1091189391144,1091189391138","skuName":"白色/XXL","skuid":1091189391151},{"barcode":"003001","invId":10921949195,"memberprice":0,"number":"003_1","retailPrice":200,"salePrice":200,"skuAssistId":"10921949135,10921949126","skuName":"红色/L","skuid":10921949191},{"barcode":"003002","invId":10921949195,"memberprice":0,"number":"003_2","retailPrice":195,"salePrice":195,"skuAssistId":"10921949135,10921949128","skuName":"红色/M","skuid":10921949192},{"barcode":"003003","invId":10921949195,"memberprice":0,"number":"003_3","retailPrice":200,"salePrice":200,"skuAssistId":"10921949137,10921949126","skuName":"蓝色/L","skuid":10921949193},{"barcode":"","invId":10921949195,"memberprice":0,"number":"003_4","retailPrice":200,"salePrice":200,"skuAssistId":"10921949137,10921949128","skuName":"蓝色/M","skuid":10921949194}],"unitTypeId":10921949105,"unitTypeName":"服装","unitid":10921949118,"unitname":"件"},{"auxpropid":10921949192,"auxpropname":"红色/M","barcode":"003002","brandName":"","categoryName":"服装","isSerNum":0,"itemid":10921949195,"memberprice":0,"name":"耐克运动衣","number":"003","productModel":"规格型号哈哈","qty":4997,"reatailprice":195,"skuName":"红色/M","skuNumber":"003_2","skuid":10921949192,"skus":[{"barcode":"","invId":10921949195,"memberprice":0,"number":"003_5","retailPrice":200,"salePrice":200,"skuAssistId":"1091189391144,1091189391136","skuName":"白色/XL","skuid":1091189391150},{"barcode":"","invId":10921949195,"memberprice":0,"number":"003_6","retailPrice":200,"salePrice":200,"skuAssistId":"1091189391144,1091189391138","skuName":"白色/XXL","skuid":1091189391151},{"barcode":"003001","invId":10921949195,"memberprice":0,"number":"003_1","retailPrice":200,"salePrice":200,"skuAssistId":"10921949135,10921949126","skuName":"红色/L","skuid":10921949191},{"barcode":"003002","invId":10921949195,"memberprice":0,"number":"003_2","retailPrice":195,"salePrice":195,"skuAssistId":"10921949135,10921949128","skuName":"红色/M","skuid":10921949192},{"barcode":"003003","invId":10921949195,"memberprice":0,"number":"003_3","retailPrice":200,"salePrice":200,"skuAssistId":"10921949137,10921949126","skuName":"蓝色/L","skuid":10921949193},{"barcode":"","invId":10921949195,"memberprice":0,"number":"003_4","retailPrice":200,"salePrice":200,"skuAssistId":"10921949137,10921949128","skuName":"蓝色/M","skuid":10921949194}],"unitTypeId":10921949105,"unitTypeName":"服装","unitid":10921949118,"unitname":"件"},{"auxpropid":10921949193,"auxpropname":"蓝色/L","barcode":"003003","brandName":"","categoryName":"服装","isSerNum":0,"itemid":10921949195,"memberprice":0,"name":"耐克运动衣","number":"003","productModel":"规格型号哈哈","qty":4988,"reatailprice":200,"skuName":"蓝色/L","skuNumber":"003_3","skuid":10921949193,"skus":[{"barcode":"","invId":10921949195,"memberprice":0,"number":"003_5","retailPrice":200,"salePrice":200,"skuAssistId":"1091189391144,1091189391136","skuName":"白色/XL","skuid":1091189391150},{"barcode":"","invId":10921949195,"memberprice":0,"number":"003_6","retailPrice":200,"salePrice":200,"skuAssistId":"1091189391144,1091189391138","skuName":"白色/XXL","skuid":1091189391151},{"barcode":"003001","invId":10921949195,"memberprice":0,"number":"003_1","retailPrice":200,"salePrice":200,"skuAssistId":"10921949135,10921949126","skuName":"红色/L","skuid":10921949191},{"barcode":"003002","invId":10921949195,"memberprice":0,"number":"003_2","retailPrice":195,"salePrice":195,"skuAssistId":"10921949135,10921949128","skuName":"红色/M","skuid":10921949192},{"barcode":"003003","invId":10921949195,"memberprice":0,"number":"003_3","retailPrice":200,"salePrice":200,"skuAssistId":"10921949137,10921949126","skuName":"蓝色/L","skuid":10921949193},{"barcode":"","invId":10921949195,"memberprice":0,"number":"003_4","retailPrice":200,"salePrice":200,"skuAssistId":"10921949137,10921949128","skuName":"蓝色/M","skuid":10921949194}],"unitTypeId":10921949105,"unitTypeName":"服装","unitid":10921949118,"unitname":"件"},{"auxpropid":10921949194,"auxpropname":"蓝色/M","barcode":"","brandName":"","categoryName":"服装","isSerNum":0,"itemid":10921949195,"memberprice":0,"name":"耐克运动衣","number":"003","productModel":"规格型号哈哈","qty":4986,"reatailprice":200,"skuName":"蓝色/M","skuNumber":"003_4","skuid":10921949194,"skus":[{"barcode":"","invId":10921949195,"memberprice":0,"number":"003_5","retailPrice":200,"salePrice":200,"skuAssistId":"1091189391144,1091189391136","skuName":"白色/XL","skuid":1091189391150},{"barcode":"","invId":10921949195,"memberprice":0,"number":"003_6","retailPrice":200,"salePrice":200,"skuAssistId":"1091189391144,1091189391138","skuName":"白色/XXL","skuid":1091189391151},{"barcode":"003001","invId":10921949195,"memberprice":0,"number":"003_1","retailPrice":200,"salePrice":200,"skuAssistId":"10921949135,10921949126","skuName":"红色/L","skuid":10921949191},{"barcode":"003002","invId":10921949195,"memberprice":0,"number":"003_2","retailPrice":195,"salePrice":195,"skuAssistId":"10921949135,10921949128","skuName":"红色/M","skuid":10921949192},{"barcode":"003003","invId":10921949195,"memberprice":0,"number":"003_3","retailPrice":200,"salePrice":200,"skuAssistId":"10921949137,10921949126","skuName":"蓝色/L","skuid":10921949193},{"barcode":"","invId":10921949195,"memberprice":0,"number":"003_4","retailPrice":200,"salePrice":200,"skuAssistId":"10921949137,10921949128","skuName":"蓝色/M","skuid":10921949194}],"unitTypeId":10921949105,"unitTypeName":"服装","unitid":10921949118,"unitname":"件"},{"auxpropid":0,"auxpropname":"","barcode":"","brandName":"","categoryName":"小百货","isSerNum":0,"itemid":109379139154,"memberprice":0,"name":"测试删除0091","number":"0091","productModel":"","qty":0,"reatailprice":0,"skuName":"","skuNumber":"0091","skuid":0,"skus":[],"unitTypeId":109105939638,"unitTypeName":"计量","unitid":109105939642,"unitname":"个"},{"auxpropid":0,"auxpropname":"","barcode":"","brandName":"","categoryName":"小百货","isSerNum":0,"itemid":1095197928,"memberprice":0,"name":"删除测试0092","number":"0092","productModel":"","qty":0,"reatailprice":0,"skuName":"","skuNumber":"0092","skuid":0,"skus":[],"unitTypeId":10937913966,"unitTypeName":"生鲜","unitid":10937913970,"unitname":"斤"},{"auxpropid":0,"auxpropname":"","barcode":"69100531002","brandName":"","categoryName":"数码3C","isSerNum":1,"itemid":109459159364,"memberprice":0,"name":"序列号100531002","number":"100531002","productModel":"","qty":0,"reatailprice":0,"skuName":"","skuNumber":"100531002","skuid":0,"skus":[],"unitTypeId":109105939638,"unitTypeName":"计量","unitid":109105939642,"unitname":"个"},{"auxpropid":0,"auxpropname":"","barcode":"","brandName":"","categoryName":"小百货","isSerNum":0,"itemid":1093291091070,"memberprice":9,"name":"验证测试普通商品","number":"180521001","productModel":"","qty":2,"reatailprice":15,"skuName":"","skuNumber":"180521001","skuid":0,"skus":[],"unitTypeId":10912899211,"unitTypeName":"刀","unitid":10912899215,"unitname":"把"},{"auxpropid":0,"auxpropname":"","barcode":"69180521002","brandName":"","categoryName":"小百货","isSerNum":0,"itemid":1093291091118,"memberprice":9,"name":"验证测试普通商品2","number":"180521002","productModel":"","qty":0,"reatailprice":15,"skuName":"","skuNumber":"180521002","skuid":0,"skus":[],"unitTypeId":10912899211,"unitTypeName":"刀","unitid":10912899215,"unitname":"把"},{"auxpropid":0,"auxpropname":"","barcode":"","brandName":"","categoryName":"小百货","isSerNum":0,"itemid":1096691097,"memberprice":24,"name":"批号商品1","number":"180528001","productModel":"","qty":6,"reatailprice":25,"skuName":"","skuNumber":"180528001","skuid":0,"skus":[],"unitTypeId":109105939638,"unitTypeName":"计量","unitid":109105939642,"unitname":"个"},{"auxpropid":0,"auxpropname":"","barcode":"","brandName":"","categoryName":"小百货","isSerNum":0,"itemid":10966910918,"memberprice":24,"name":"批号多单位商品","number":"180528002","prices":[{"id":10966910939,"inventoryId":10966910918,"purPrice":0,"retailPrice":20,"salePrice":25,"salePrice1":24,"salePrice2":85,"salePrice3":95,"unitId":109105939642,"unitTypeId":109105939638},{"id":10966910940,"inventoryId":10966910918,"purPrice":0,"retailPrice":115,"salePrice":145,"salePrice1":144,"salePrice2":80,"salePrice3":90,"unitId":109105939646,"unitTypeId":109105939638}],"productModel":"","qty":6,"reatailprice":25,"skuName":"","skuNumber":"180528002","skuid":0,"skus":[],"unitTypeId":109105939638,"unitTypeName":"计量","unitid":109105939642,"unitname":"个"},{"auxpropid":0,"auxpropname":"","barcode":"69180531001","brandName":"","categoryName":"小百货","isSerNum":0,"itemid":109459159347,"memberprice":90,"name":"普通商品180531001","number":"180531001","prices":[{"id":109459159356,"inventoryId":109459159347,"purPrice":0,"retailPrice":100,"salePrice":120,"salePrice1":90,"salePrice2":70,"salePrice3":60,"unitId":109105939642,"unitTypeId":109105939638},{"id":109459159357,"inventoryId":109459159347,"purPrice":0,"retailPrice":300,"salePrice":360,"salePrice1":160,"salePrice2":70,"salePrice3":60,"unitId":109105939646,"unitTypeId":109105939638}],"productModel":"","qty":0,"reatailprice":120,"skuName":"","skuNumber":"180531001","skuid":0,"skus":[],"unitTypeId":109105939638,"unitTypeName":"计量","unitid":109105939642,"unitname":"个"},{"auxpropid":0,"auxpropname":"","barcode":"69180531002","brandName":"","categoryName":"数码3C","isSerNum":1,"itemid":109459159425,"memberprice":45,"name":"序列号180531002","number":"180531002","productModel":"","qty":0,"reatailprice":60,"skuName":"","skuNumber":"180531002","skuid":0,"skus":[],"unitTypeId":109105939638,"unitTypeName":"计量","unitid":109105939642,"unitname":"个"},{"auxpropid":10921949191,"auxpropname":"红色/L","barcode":"6918053100301","brandName":"","categoryName":"服装","isSerNum":0,"itemid":109459159380,"memberprice":45,"name":"辅助属性衣服180531003","number":"180531003","productModel":"","qty":0,"reatailprice":60,"skuName":"红色/L","skuNumber":"180531003_1","skuid":10921949191,"skus":[{"barcode":"6918053100301","invId":109459159380,"memberprice":45,"number":"180531003_1","retailPrice":60,"salePrice":60,"skuAssistId":"10921949135,10921949126","skuName":"红色/L","skuid":10921949191},{"barcode":"69180531002","invId":109459159380,"memberprice":0,"number":"180531003_2","retailPrice":0,"salePrice":0,"skuAssistId":"10921949135,10921949128","skuName":"红色/M","skuid":10921949192},{"barcode":"6918053100303","invId":109459159380,"memberprice":0,"number":"180531003_3","retailPrice":0,"salePrice":0,"skuAssistId":"10921949135,10921949130","skuName":"红色/S","skuid":109118939140},{"barcode":"6918053100304","invId":109459159380,"memberprice":0,"number":"180531003_4","retailPrice":0,"salePrice":0,"skuAssistId":"10921949137,10921949126","skuName":"蓝色/L","skuid":10921949193},{"barcode":"6918053100305","invId":109459159380,"memberprice":0,"number":"180531003_5","retailPrice":0,"salePrice":0,"skuAssistId":"10921949137,10921949128","skuName":"蓝色/M","skuid":10921949194},{"barcode":"6918053100306","invId":109459159380,"memberprice":0,"number":"180531003_6","retailPrice":0,"salePrice":0,"skuAssistId":"10921949137,10921949130","skuName":"蓝色/S","skuid":109118939141}],"unitTypeId":-1,"unitTypeName":"默认单位组","unitid":-1,"unitname":"件"},{"auxpropid":10921949192,"auxpropname":"红色/M","barcode":"69180531002","brandName":"","categoryName":"服装","isSerNum":0,"itemid":109459159380,"memberprice":0,"name":"辅助属性衣服180531003","number":"180531003","productModel":"","qty":0,"reatailprice":0,"skuName":"红色/M","skuNumber":"180531003_2","skuid":10921949192,"skus":[{"barcode":"6918053100301","invId":109459159380,"memberprice":45,"number":"180531003_1","retailPrice":60,"salePrice":60,"skuAssistId":"10921949135,10921949126","skuName":"红色/L","skuid":10921949191},{"barcode":"69180531002","invId":109459159380,"memberprice":0,"number":"180531003_2","retailPrice":0,"salePrice":0,"skuAssistId":"10921949135,10921949128","skuName":"红色/M","skuid":10921949192},{"barcode":"6918053100303","invId":109459159380,"memberprice":0,"number":"180531003_3","retailPrice":0,"salePrice":0,"skuAssistId":"10921949135,10921949130","skuName":"红色/S","skuid":109118939140},{"barcode":"6918053100304","invId":109459159380,"memberprice":0,"number":"180531003_4","retailPrice":0,"salePrice":0,"skuAssistId":"10921949137,10921949126","skuName":"蓝色/L","skuid":10921949193},{"barcode":"6918053100305","invId":109459159380,"memberprice":0,"number":"180531003_5","retailPrice":0,"salePrice":0,"skuAssistId":"10921949137,10921949128","skuName":"蓝色/M","skuid":10921949194},{"barcode":"6918053100306","invId":109459159380,"memberprice":0,"number":"180531003_6","retailPrice":0,"salePrice":0,"skuAssistId":"10921949137,10921949130","skuName":"蓝色/S","skuid":109118939141}],"unitTypeId":-1,"unitTypeName":"默认单位组","unitid":-1,"unitname":"件"},{"auxpropid":109118939140,"auxpropname":"红色/S","barcode":"6918053100303","brandName":"","categoryName":"服装","isSerNum":0,"itemid":109459159380,"memberprice":0,"name":"辅助属性衣服180531003","number":"180531003","productModel":"","qty":0,"reatailprice":0,"skuName":"红色/S","skuNumber":"180531003_3","skuid":109118939140,"skus":[{"barcode":"6918053100301","invId":109459159380,"memberprice":45,"number":"180531003_1","retailPrice":60,"salePrice":60,"skuAssistId":"10921949135,10921949126","skuName":"红色/L","skuid":10921949191},{"barcode":"69180531002","invId":109459159380,"memberprice":0,"number":"180531003_2","retailPrice":0,"salePrice":0,"skuAssistId":"10921949135,10921949128","skuName":"红色/M","skuid":10921949192},{"barcode":"6918053100303","invId":109459159380,"memberprice":0,"number":"180531003_3","retailPrice":0,"salePrice":0,"skuAssistId":"10921949135,10921949130","skuName":"红色/S","skuid":109118939140},{"barcode":"6918053100304","invId":109459159380,"memberprice":0,"number":"180531003_4","retailPrice":0,"salePrice":0,"skuAssistId":"10921949137,10921949126","skuName":"蓝色/L","skuid":10921949193},{"barcode":"6918053100305","invId":109459159380,"memberprice":0,"number":"180531003_5","retailPrice":0,"salePrice":0,"skuAssistId":"10921949137,10921949128","skuName":"蓝色/M","skuid":10921949194},{"barcode":"6918053100306","invId":109459159380,"memberprice":0,"number":"180531003_6","retailPrice":0,"salePrice":0,"skuAssistId":"10921949137,10921949130","skuName":"蓝色/S","skuid":109118939141}],"unitTypeId":-1,"unitTypeName":"默认单位组","unitid":-1,"unitname":"件"},{"auxpropid":10921949193,"auxpropname":"蓝色/L","barcode":"6918053100304","brandName":"","categoryName":"服装","isSerNum":0,"itemid":109459159380,"memberprice":0,"name":"辅助属性衣服180531003","number":"180531003","productModel":"","qty":0,"reatailprice":0,"skuName":"蓝色/L","skuNumber":"180531003_4","skuid":10921949193,"skus":[{"barcode":"6918053100301","invId":109459159380,"memberprice":45,"number":"180531003_1","retailPrice":60,"salePrice":60,"skuAssistId":"10921949135,10921949126","skuName":"红色/L","skuid":10921949191},{"barcode":"69180531002","invId":109459159380,"memberprice":0,"number":"180531003_2","retailPrice":0,"salePrice":0,"skuAssistId":"10921949135,10921949128","skuName":"红色/M","skuid":10921949192},{"barcode":"6918053100303","invId":109459159380,"memberprice":0,"number":"180531003_3","retailPrice":0,"salePrice":0,"skuAssistId":"10921949135,10921949130","skuName":"红色/S","skuid":109118939140},{"barcode":"6918053100304","invId":109459159380,"memberprice":0,"number":"180531003_4","retailPrice":0,"salePrice":0,"skuAssistId":"10921949137,10921949126","skuName":"蓝色/L","skuid":10921949193},{"barcode":"6918053100305","invId":109459159380,"memberprice":0,"number":"180531003_5","retailPrice":0,"salePrice":0,"skuAssistId":"10921949137,10921949128","skuName":"蓝色/M","skuid":10921949194},{"barcode":"6918053100306","invId":109459159380,"memberprice":0,"number":"180531003_6","retailPrice":0,"salePrice":0,"skuAssistId":"10921949137,10921949130","skuName":"蓝色/S","skuid":109118939141}],"unitTypeId":-1,"unitTypeName":"默认单位组","unitid":-1,"unitname":"件"},{"auxpropid":10921949194,"auxpropname":"蓝色/M","barcode":"6918053100305","brandName":"","categoryName":"服装","isSerNum":0,"itemid":109459159380,"memberprice":0,"name":"辅助属性衣服180531003","number":"180531003","productModel":"","qty":0,"reatailprice":0,"skuName":"蓝色/M","skuNumber":"180531003_5","skuid":10921949194,"skus":[{"barcode":"6918053100301","invId":109459159380,"memberprice":45,"number":"180531003_1","retailPrice":60,"salePrice":60,"skuAssistId":"10921949135,10921949126","skuName":"红色/L","skuid":10921949191},{"barcode":"69180531002","invId":109459159380,"memberprice":0,"number":"180531003_2","retailPrice":0,"salePrice":0,"skuAssistId":"10921949135,10921949128","skuName":"红色/M","skuid":10921949192},{"barcode":"6918053100303","invId":109459159380,"memberprice":0,"number":"180531003_3","retailPrice":0,"salePrice":0,"skuAssistId":"10921949135,10921949130","skuName":"红色/S","skuid":109118939140},{"barcode":"6918053100304","invId":109459159380,"memberprice":0,"number":"180531003_4","retailPrice":0,"salePrice":0,"skuAssistId":"10921949137,10921949126","skuName":"蓝色/L","skuid":10921949193},{"barcode":"6918053100305","invId":109459159380,"memberprice":0,"number":"180531003_5","retailPrice":0,"salePrice":0,"skuAssistId":"10921949137,10921949128","skuName":"蓝色/M","skuid":10921949194},{"barcode":"6918053100306","invId":109459159380,"memberprice":0,"number":"180531003_6","retailPrice":0,"salePrice":0,"skuAssistId":"10921949137,10921949130","skuName":"蓝色/S","skuid":109118939141}],"unitTypeId":-1,"unitTypeName":"默认单位组","unitid":-1,"unitname":"件"},{"auxpropid":109118939141,"auxpropname":"蓝色/S","barcode":"6918053100306","brandName":"","categoryName":"服装","isSerNum":0,"itemid":109459159380,"memberprice":0,"name":"辅助属性衣服180531003","number":"180531003","productModel":"","qty":0,"reatailprice":0,"skuName":"蓝色/S","skuNumber":"180531003_6","skuid":109118939141,"skus":[{"barcode":"6918053100301","invId":109459159380,"memberprice":45,"number":"180531003_1","retailPrice":60,"salePrice":60,"skuAssistId":"10921949135,10921949126","skuName":"红色/L","skuid":10921949191},{"barcode":"69180531002","invId":109459159380,"memberprice":0,"number":"180531003_2","retailPrice":0,"salePrice":0,"skuAssistId":"10921949135,10921949128","skuName":"红色/M","skuid":10921949192},{"barcode":"6918053100303","invId":109459159380,"memberprice":0,"number":"180531003_3","retailPrice":0,"salePrice":0,"skuAssistId":"10921949135,10921949130","skuName":"红色/S","skuid":109118939140},{"barcode":"6918053100304","invId":109459159380,"memberprice":0,"number":"180531003_4","retailPrice":0,"salePrice":0,"skuAssistId":"10921949137,10921949126","skuName":"蓝色/L","skuid":10921949193},{"barcode":"6918053100305","invId":109459159380,"memberprice":0,"number":"180531003_5","retailPrice":0,"salePrice":0,"skuAssistId":"10921949137,10921949128","skuName":"蓝色/M","skuid":10921949194},{"barcode":"6918053100306","invId":109459159380,"memberprice":0,"number":"180531003_6","retailPrice":0,"salePrice":0,"skuAssistId":"10921949137,10921949130","skuName":"蓝色/S","skuid":109118939141}],"unitTypeId":-1,"unitTypeName":"默认单位组","unitid":-1,"unitname":"件"},{"auxpropid":0,"auxpropname":"","barcode":"6256","brandName":"","categoryName":"水果","isSerNum":0,"itemid":109201919610,"memberprice":0,"name":"红富士苹果","number":"1806080001","productModel":"","qty":0,"reatailprice":8.98,"skuName":"","skuNumber":"1806080001","skuid":0,"skus":[],"unitTypeId":10937913966,"unitTypeName":"生鲜","unitid":109201919603,"unitname":"KG"},{"auxpropid":0,"auxpropname":"","barcode":"69522001","brandName":"","categoryName":"小百货","isSerNum":0,"itemid":10948989103,"memberprice":0,"name":"普通商品多单位","number":"522001","prices":[{"id":10948989108,"inventoryId":10948989103,"purPrice":0,"retailPrice":10,"salePrice":15,"salePrice1":0,"salePrice2":95,"salePrice3":80,"unitId":109105939642,"unitTypeId":109105939638},{"id":10948989133,"inventoryId":10948989103,"purPrice":0,"retailPrice":76,"salePrice":110,"salePrice1":0,"salePrice2":90,"salePrice3":70,"unitId":109105939650,"unitTypeId":109105939638}],"productModel":"","qty":1,"reatailprice":15,"skuName":"","skuNumber":"522001","skuid":0,"skus":[],"unitTypeId":109105939638,"unitTypeName":"计量","unitid":109105939642,"unitname":"个"},{"auxpropid":0,"auxpropname":"","barcode":"69523003","brandName":"","categoryName":"默认分类","isSerNum":1,"itemid":10948989375,"memberprice":42,"name":"验证序列号商品","number":"523003","productModel":"","qty":56,"reatailprice":50,"skuName":"","skuNumber":"523003","skuid":0,"skus":[],"unitTypeId":109105939638,"unitTypeName":"计量","unitid":109105939642,"unitname":"个"},{"auxpropid":0,"auxpropname":"","barcode":"","brandName":"","categoryName":"小百货","isSerNum":0,"itemid":10937913955,"memberprice":0,"name":"批次小商铺","number":"SP0066","productModel":"","qty":0,"reatailprice":0,"skuName":"","skuNumber":"SP0066","skuid":0,"skus":[],"unitTypeId":-1,"unitTypeName":"默认单位组","unitid":-1,"unitname":"件"},{"auxpropid":0,"auxpropname":"","barcode":"","brandName":"","categoryName":"小百货","isSerNum":0,"itemid":10945913986,"memberprice":0,"name":"大商品2","number":"SP20180516002","productModel":"","qty":1,"reatailprice":0,"skuName":"","skuNumber":"SP20180516002","skuid":0,"skus":[],"unitTypeId":-1,"unitTypeName":"默认单位组","unitid":-1,"unitname":"件"},{"auxpropid":0,"auxpropname":"","barcode":"","brandName":"","categoryName":"小百货","isSerNum":0,"itemid":109459139100,"memberprice":0,"name":"大商品3","number":"SP20180516003","productModel":"","qty":0,"reatailprice":0,"skuName":"","skuNumber":"SP20180516003","skuid":0,"skus":[],"unitTypeId":-1,"unitTypeName":"默认单位组","unitid":-1,"unitname":"件"},{"auxpropid":0,"auxpropname":"","barcode":"","brandName":"","categoryName":"小百货","isSerNum":0,"itemid":109459139109,"memberprice":0,"name":"大商品9","number":"SP20180516009","productModel":"","qty":0,"reatailprice":0,"skuName":"","skuNumber":"SP20180516009","skuid":0,"skus":[],"unitTypeId":-1,"unitTypeName":"默认单位组","unitid":-1,"unitname":"件"},{"auxpropid":0,"auxpropname":"","barcode":"","brandName":"","categoryName":"小百货","isSerNum":0,"itemid":109459139139,"memberprice":0,"name":"大商品10","number":"SP20180516010","productModel":"","qty":0,"reatailprice":0,"skuName":"","skuNumber":"SP20180516010","skuid":0,"skus":[],"unitTypeId":-1,"unitTypeName":"默认单位组","unitid":-1,"unitname":"件"},{"auxpropid":0,"auxpropname":"","barcode":"","brandName":"","categoryName":"小百货","isSerNum":0,"itemid":109459139145,"memberprice":0,"name":"大商品11","number":"SP20180516011","productModel":"","qty":0,"reatailprice":0,"skuName":"","skuNumber":"SP20180516011","skuid":0,"skus":[],"unitTypeId":-1,"unitTypeName":"默认单位组","unitid":-1,"unitname":"件"},{"auxpropid":0,"auxpropname":"","barcode":"","brandName":"","categoryName":"小百货","isSerNum":0,"itemid":109459139151,"memberprice":0,"name":"大商品12","number":"SP20180516012","productModel":"","qty":0,"reatailprice":0,"skuName":"","skuNumber":"SP20180516012","skuid":0,"skus":[],"unitTypeId":-1,"unitTypeName":"默认单位组","unitid":-1,"unitname":"件"},{"auxpropid":0,"auxpropname":"","barcode":"","brandName":"","categoryName":"小百货","isSerNum":0,"itemid":109459139157,"memberprice":0,"name":"大商品13","number":"SP20180516013","productModel":"","qty":2,"reatailprice":0,"skuName":"","skuNumber":"SP20180516013","skuid":0,"skus":[],"unitTypeId":10912899211,"unitTypeName":"刀","unitid":10912899215,"unitname":"把"},{"auxpropid":0,"auxpropname":"","barcode":"","brandName":"","categoryName":"小百货","isSerNum":0,"itemid":109459139212,"memberprice":0,"name":"大商品20","number":"SP20180516020","productModel":"","qty":0,"reatailprice":0,"skuName":"","skuNumber":"SP20180516020","skuid":0,"skus":[],"unitTypeId":10912899211,"unitTypeName":"刀","unitid":10912899215,"unitname":"把"},{"auxpropid":0,"auxpropname":"","barcode":"","brandName":"","categoryName":"小百货","isSerNum":0,"itemid":109459139218,"memberprice":0,"name":"大商品21","number":"SP20180516021","productModel":"","qty":0,"reatailprice":0,"skuName":"","skuNumber":"SP20180516021","skuid":0,"skus":[],"unitTypeId":-1,"unitTypeName":"默认单位组","unitid":-1,"unitname":"件"},{"auxpropid":0,"auxpropname":"","barcode":"","brandName":"","categoryName":"小百货","isSerNum":0,"itemid":109459139227,"memberprice":0,"name":"大商品22","number":"SP20180516022","productModel":"","qty":0,"reatailprice":0,"skuName":"","skuNumber":"SP20180516022","skuid":0,"skus":[],"unitTypeId":-1,"unitTypeName":"默认单位组","unitid":-1,"unitname":"件"},{"auxpropid":0,"auxpropname":"","barcode":"","brandName":"","categoryName":"小百货","isSerNum":0,"itemid":109459139233,"memberprice":0,"name":"大商品23","number":"SP20180516023","productModel":"","qty":1,"reatailprice":0,"skuName":"","skuNumber":"SP20180516023","skuid":0,"skus":[],"unitTypeId":-1,"unitTypeName":"默认单位组","unitid":-1,"unitname":"件"},{"auxpropid":0,"auxpropname":"","barcode":"","brandName":"","categoryName":"小百货","isSerNum":0,"itemid":109459139239,"memberprice":0,"name":"大商品24","number":"SP20180516024","productModel":"","qty":0,"reatailprice":0,"skuName":"","skuNumber":"SP20180516024","skuid":0,"skus":[],"unitTypeId":-1,"unitTypeName":"默认单位组","unitid":-1,"unitname":"件"},{"auxpropid":0,"auxpropname":"","barcode":"","brandName":"","categoryName":"数码3C","isSerNum":0,"itemid":109459139245,"memberprice":0,"name":"大商品25","number":"SP20180516025","productModel":"","qty":0,"reatailprice":0,"skuName":"","skuNumber":"SP20180516025","skuid":0,"skus":[],"unitTypeId":-1,"unitTypeName":"默认单位组","unitid":-1,"unitname":"件"},{"auxpropid":0,"auxpropname":"","barcode":"","brandName":"","categoryName":"小百货","isSerNum":0,"itemid":109459139251,"memberprice":0,"name":"大商品26","number":"SP20180516026","productModel":"","qty":0,"reatailprice":0,"skuName":"","skuNumber":"SP20180516026","skuid":0,"skus":[],"unitTypeId":-1,"unitTypeName":"默认单位组","unitid":-1,"unitname":"件"},{"auxpropid":0,"auxpropname":"","barcode":"","brandName":"","categoryName":"小百货","isSerNum":0,"itemid":109459139257,"memberprice":0,"name":"大商品27","number":"SP20180516027","productModel":"","qty":0,"reatailprice":0,"skuName":"","skuNumber":"SP20180516027","skuid":0,"skus":[],"unitTypeId":-1,"unitTypeName":"默认单位组","unitid":-1,"unitname":"件"},{"auxpropid":0,"auxpropname":"","barcode":"","brandName":"","categoryName":"小百货","isSerNum":0,"itemid":109459139263,"memberprice":0,"name":"大商品28","number":"SP20180516028","productModel":"","qty":0,"reatailprice":0,"skuName":"","skuNumber":"SP20180516028","skuid":0,"skus":[],"unitTypeId":10912899211,"unitTypeName":"刀","unitid":10912899215,"unitname":"把"},{"auxpropid":0,"auxpropname":"","barcode":"","brandName":"","categoryName":"小百货","isSerNum":0,"itemid":109459139269,"memberprice":0,"name":"大商品29","number":"SP20180516029","productModel":"","qty":0,"reatailprice":0,"skuName":"","skuNumber":"SP20180516029","skuid":0,"skus":[],"unitTypeId":-1,"unitTypeName":"默认单位组","unitid":-1,"unitname":"件"},{"auxpropid":0,"auxpropname":"","barcode":"","brandName":"","categoryName":"数码3C","isSerNum":0,"itemid":109459139275,"memberprice":0,"name":"大商品30","number":"SP20180516030","productModel":"","qty":0,"reatailprice":0,"skuName":"","skuNumber":"SP20180516030","skuid":0,"skus":[],"unitTypeId":10912899211,"unitTypeName":"刀","unitid":10912899215,"unitname":"把"},{"auxpropid":0,"auxpropname":"","barcode":"","brandName":"","categoryName":"数码3C","isSerNum":0,"itemid":109459139281,"memberprice":0,"name":"大商品31","number":"SP20180516031","productModel":"","qty":0,"reatailprice":0,"skuName":"","skuNumber":"SP20180516031","skuid":0,"skus":[],"unitTypeId":-1,"unitTypeName":"默认单位组","unitid":-1,"unitname":"件"},{"auxpropid":0,"auxpropname":"","barcode":"","brandName":"","categoryName":"小百货","isSerNum":0,"itemid":109459139290,"memberprice":0,"name":"大商品32","number":"SP20180516032","productModel":"","qty":0,"reatailprice":0,"skuName":"","skuNumber":"SP20180516032","skuid":0,"skus":[],"unitTypeId":-1,"unitTypeName":"默认单位组","unitid":-1,"unitname":"件"},{"auxpropid":0,"auxpropname":"","barcode":"","brandName":"","categoryName":"小百货","isSerNum":0,"itemid":109459139297,"memberprice":0,"name":"大商品33","number":"SP20180516033","productModel":"","qty":0,"reatailprice":0,"skuName":"","skuNumber":"SP20180516033","skuid":0,"skus":[],"unitTypeId":-1,"unitTypeName":"默认单位组","unitid":-1,"unitname":"件"},{"auxpropid":0,"auxpropname":"","barcode":"","brandName":"","categoryName":"小百货","isSerNum":0,"itemid":109459139304,"memberprice":0,"name":"大商品34","number":"SP20180516034","productModel":"","qty":0,"reatailprice":0,"skuName":"","skuNumber":"SP20180516034","skuid":0,"skus":[],"unitTypeId":-1,"unitTypeName":"默认单位组","unitid":-1,"unitname":"件"},{"auxpropid":0,"auxpropname":"","barcode":"","brandName":"","categoryName":"小百货","isSerNum":0,"itemid":109459139310,"memberprice":0,"name":"大商品35","number":"SP20180516035","productModel":"","qty":0,"reatailprice":0,"skuName":"","skuNumber":"SP20180516035","skuid":0,"skus":[],"unitTypeId":10912899211,"unitTypeName":"刀","unitid":10912899215,"unitname":"把"},{"auxpropid":0,"auxpropname":"","barcode":"","brandName":"","categoryName":"数码3C","isSerNum":0,"itemid":109459139318,"memberprice":0,"name":"大商品36","number":"SP20180516036","productModel":"","qty":0,"reatailprice":0,"skuName":"","skuNumber":"SP20180516036","skuid":0,"skus":[],"unitTypeId":-1,"unitTypeName":"默认单位组","unitid":-1,"unitname":"件"},{"auxpropid":0,"auxpropname":"","barcode":"","brandName":"","categoryName":"小百货","isSerNum":0,"itemid":109459139325,"memberprice":0,"name":"大商品37","number":"SP20180516037","productModel":"","qty":0,"reatailprice":0,"skuName":"","skuNumber":"SP20180516037","skuid":0,"skus":[],"unitTypeId":-1,"unitTypeName":"默认单位组","unitid":-1,"unitname":"件"},{"auxpropid":0,"auxpropname":"","barcode":"","brandName":"","categoryName":"小百货","isSerNum":0,"itemid":109459139338,"memberprice":0,"name":"大商品38","number":"SP20180516038","productModel":"","qty":0,"reatailprice":0,"skuName":"","skuNumber":"SP20180516038","skuid":0,"skus":[],"unitTypeId":-1,"unitTypeName":"默认单位组","unitid":-1,"unitname":"件"},{"auxpropid":0,"auxpropname":"","barcode":"","brandName":"","categoryName":"小百货","isSerNum":0,"itemid":109459139344,"memberprice":0,"name":"大商品39","number":"SP20180516039","productModel":"","qty":0,"reatailprice":0,"skuName":"","skuNumber":"SP20180516039","skuid":0,"skus":[],"unitTypeId":-1,"unitTypeName":"默认单位组","unitid":-1,"unitname":"件"},{"auxpropid":0,"auxpropname":"","barcode":"","brandName":"","categoryName":"小百货","isSerNum":0,"itemid":109459139353,"memberprice":0,"name":"大商品40","number":"SP20180516040","productModel":"","qty":0,"reatailprice":0,"skuName":"","skuNumber":"SP20180516040","skuid":0,"skus":[],"unitTypeId":-1,"unitTypeName":"默认单位组","unitid":-1,"unitname":"件"},{"auxpropid":0,"auxpropname":"","barcode":"","brandName":"","categoryName":"小百货","isSerNum":0,"itemid":109459139362,"memberprice":0,"name":"大商品41","number":"SP20180516041","productModel":"","qty":0,"reatailprice":0,"skuName":"","skuNumber":"SP20180516041","skuid":0,"skus":[],"unitTypeId":-1,"unitTypeName":"默认单位组","unitid":-1,"unitname":"件"},{"auxpropid":0,"auxpropname":"","barcode":"","brandName":"","categoryName":"小百货","isSerNum":0,"itemid":109459139368,"memberprice":0,"name":"大商品42","number":"SP20180516042","productModel":"","qty":0,"reatailprice":0,"skuName":"","skuNumber":"SP20180516042","skuid":0,"skus":[],"unitTypeId":-1,"unitTypeName":"默认单位组","unitid":-1,"unitname":"件"},{"auxpropid":0,"auxpropname":"","barcode":"","brandName":"","categoryName":"小百货","isSerNum":0,"itemid":109459139374,"memberprice":0,"name":"大商品43","number":"SP20180516043","productModel":"","qty":0,"reatailprice":0,"skuName":"","skuNumber":"SP20180516043","skuid":0,"skus":[],"unitTypeId":-1,"unitTypeName":"默认单位组","unitid":-1,"unitname":"件"},{"auxpropid":0,"auxpropname":"","barcode":"","brandName":"","categoryName":"小百货","isSerNum":0,"itemid":109459139380,"memberprice":0,"name":"大商品44","number":"SP20180516044","productModel":"","qty":0,"reatailprice":0,"skuName":"","skuNumber":"SP20180516044","skuid":0,"skus":[],"unitTypeId":-1,"unitTypeName":"默认单位组","unitid":-1,"unitname":"件"},{"auxpropid":0,"auxpropname":"","barcode":"","brandName":"","categoryName":"小百货","isSerNum":0,"itemid":109459139386,"memberprice":0,"name":"大商品45","number":"SP20180516045","productModel":"","qty":0,"reatailprice":0,"skuName":"","skuNumber":"SP20180516045","skuid":0,"skus":[],"unitTypeId":-1,"unitTypeName":"默认单位组","unitid":-1,"unitname":"件"},{"auxpropid":0,"auxpropname":"","barcode":"","brandName":"","categoryName":"小百货","isSerNum":0,"itemid":109459139392,"memberprice":0,"name":"大商品46","number":"SP20180516046","productModel":"","qty":0,"reatailprice":0,"skuName":"","skuNumber":"SP20180516046","skuid":0,"skus":[],"unitTypeId":-1,"unitTypeName":"默认单位组","unitid":-1,"unitname":"件"},{"auxpropid":0,"auxpropname":"","barcode":"","brandName":"","categoryName":"小百货","isSerNum":0,"itemid":109459139398,"memberprice":0,"name":"大商品47","number":"SP20180516047","productModel":"","qty":0,"reatailprice":0,"skuName":"","skuNumber":"SP20180516047","skuid":0,"skus":[],"unitTypeId":-1,"unitTypeName":"默认单位组","unitid":-1,"unitname":"件"},{"auxpropid":0,"auxpropname":"","barcode":"","brandName":"","categoryName":"小百货","isSerNum":0,"itemid":109459139404,"memberprice":0,"name":"大商品48","number":"SP20180516048","productModel":"","qty":0,"reatailprice":0,"skuName":"","skuNumber":"SP20180516048","skuid":0,"skus":[],"unitTypeId":-1,"unitTypeName":"默认单位组","unitid":-1,"unitname":"件"},{"auxpropid":0,"auxpropname":"","barcode":"","brandName":"","categoryName":"数码3C","isSerNum":0,"itemid":109459139410,"memberprice":0,"name":"大商品49","number":"SP20180516049","productModel":"","qty":0,"reatailprice":0,"skuName":"","skuNumber":"SP20180516049","skuid":0,"skus":[],"unitTypeId":-1,"unitTypeName":"默认单位组","unitid":-1,"unitname":"件"},{"auxpropid":0,"auxpropname":"","barcode":"","brandName":"","categoryName":"小百货","isSerNum":0,"itemid":109459139416,"memberprice":0,"name":"大商品50","number":"SP20180516050","productModel":"","qty":0,"reatailprice":0,"skuName":"","skuNumber":"SP20180516050","skuid":0,"skus":[],"unitTypeId":-1,"unitTypeName":"默认单位组","unitid":-1,"unitname":"件"},{"auxpropid":0,"auxpropname":"","barcode":"111111111","brandName":"","categoryName":"数码3C","isSerNum":0,"itemid":1095197942,"memberprice":0,"name":"sdfsdfdsf","number":"sfsdfsdfsdf","productModel":"","qty":0,"reatailprice":0,"skuName":"","skuNumber":"sfsdfsdfsdf","skuid":0,"skus":[],"unitTypeId":10921949102,"unitTypeName":"香烟","unitid":10921949109,"unitname":"包"}]},"pageResult":{"has_next":false,"pageCount":1,"pageIndex":1,"pageSize":200,"rowCount":66},"requestid":"MY1d21528790664971","result":200}